magic/__init__.py
magic/magic.py
magic/libmagic/libmagic.la
magic/libmagic/libmagic.so.1
magic/libmagic/magic.mgc
python_magic_debian_bin-0.4.25.dist-info/LICENSE
python_magic_debian_bin-0.4.25.dist-info/METADATA
python_magic_debian_bin-0.4.25.dist-info/WHEEL
python_magic_debian_bin-0.4.25.dist-info/top_level.txt
python_magic_debian_bin-0.4.25.dist-info/RECORD
