Metadata-Version: 2.1
Name: python-magic-debian-bin
Version: 0.4.25
Summary: File type identification using libmagic binary package, for debian linux
Home-page: http://github.com/spencer-hanson/python-magic
Author: Julian David Rath
Author-email: UNKNOWN
License: MIT
Keywords: mime magic file binary
Platform: UNKNOWN
Classifier: Intended Audience :: Developers
Classifier: License :: OSI Approved :: MIT License
Classifier: Programming Language :: Python
Classifier: Programming Language :: Python :: 2
Classifier: Programming Language :: Python :: 3
